<?xml version="1.0" encoding="UTF-8"?>
<DEFECTS>
  <DEFECT>
    <SFA>
      <FILEPATH>c:\users\sueyoshiii\desktop\rdirectx\dx12\dx12tutorial\dx12tutorial\</FILEPATH>
      <FILENAME>dx12wrapper.cpp</FILENAME>
      <LINE>441</LINE>
      <COLUMN>29</COLUMN>
    </SFA>
    <DEFECTCODE>6387</DEFECTCODE>
    <DESCRIPTION>'texbuff' は '0' である可能性があります: この動作は、関数 'CD3DX12_RESOURCE_BARRIER::Transition' の指定に従っていません。</DESCRIPTION>
    <FUNCTION>DX12Wrapper::InitTexture</FUNCTION>
    <DECORATED>?InitTexture@DX12Wrapper@@AEAAXXZ</DECORATED>
    <FUNCLINE>378</FUNCLINE>
    <PROBABILITY>1</PROBABILITY>
    <RANK>4</RANK>
    <CATEGORY>
      <RULECATEGORY>mspft</RULECATEGORY>
    </CATEGORY>
    <PATH>
      <SFA>
        <FILEPATH>c:\users\sueyoshiii\desktop\rdirectx\dx12\dx12tutorial\dx12tutorial\</FILEPATH>
        <FILENAME>dx12wrapper.cpp</FILENAME>
        <LINE>380</LINE>
        <COLUMN>13</COLUMN>
      </SFA>
      <SFA>
        <FILEPATH>c:\users\sueyoshiii\desktop\rdirectx\dx12\dx12tutorial\dx12tutorial\</FILEPATH>
        <FILENAME>dx12wrapper.cpp</FILENAME>
        <LINE>381</LINE>
        <COLUMN>14</COLUMN>
      </SFA>
      <SFA>
        <FILEPATH>c:\users\sueyoshiii\desktop\directxtex-master\directxtex\</FILEPATH>
        <FILENAME>directxtex.h</FILENAME>
        <LINE>392</LINE>
        <COLUMN>80</COLUMN>
      </SFA>
      <SFA>
        <FILEPATH>c:\users\sueyoshiii\desktop\rdirectx\dx12\dx12tutorial\dx12tutorial\</FILEPATH>
        <FILENAME>dx12wrapper.cpp</FILENAME>
        <LINE>382</LINE>
        <COLUMN>8</COLUMN>
      </SFA>
      <SFA>
        <FILEPATH>c:\users\sueyoshiii\desktop\rdirectx\dx12\dx12tutorial\dx12tutorial\</FILEPATH>
        <FILENAME>dx12wrapper.cpp</FILENAME>
        <LINE>384</LINE>
        <COLUMN>23</COLUMN>
      </SFA>
      <SFA>
        <FILEPATH>c:\users\sueyoshiii\desktop\rdirectx\dx12\dx12tutorial\dx12tutorial\</FILEPATH>
        <FILENAME>dx12wrapper.cpp</FILENAME>
        <LINE>385</LINE>
        <COLUMN>14</COLUMN>
      </SFA>
      <SFA>
        <FILEPATH>c:\users\sueyoshiii\desktop\rdirectx\dx12\dx12tutorial\dx12tutorial\</FILEPATH>
        <FILENAME>dx12wrapper.cpp</FILENAME>
        <LINE>386</LINE>
        <COLUMN>25</COLUMN>
      </SFA>
      <SFA>
        <FILEPATH>c:\users\sueyoshiii\desktop\rdirectx\dx12\dx12tutorial\dx12tutorial\</FILEPATH>
        <FILENAME>dx12wrapper.cpp</FILENAME>
        <LINE>387</LINE>
        <COLUMN>30</COLUMN>
      </SFA>
      <SFA>
        <FILEPATH>c:\users\sueyoshiii\desktop\rdirectx\dx12\dx12tutorial\dx12tutorial\</FILEPATH>
        <FILENAME>dx12wrapper.cpp</FILENAME>
        <LINE>388</LINE>
        <COLUMN>26</COLUMN>
      </SFA>
      <SFA>
        <FILEPATH>c:\users\sueyoshiii\desktop\rdirectx\dx12\dx12tutorial\dx12tutorial\</FILEPATH>
        <FILENAME>dx12wrapper.cpp</FILENAME>
        <LINE>389</LINE>
        <COLUMN>25</COLUMN>
      </SFA>
      <SFA>
        <FILEPATH>c:\users\sueyoshiii\desktop\rdirectx\dx12\dx12tutorial\dx12tutorial\</FILEPATH>
        <FILENAME>dx12wrapper.cpp</FILENAME>
        <LINE>391</LINE>
        <COLUMN>21</COLUMN>
      </SFA>
      <SFA>
        <FILEPATH>c:\users\sueyoshiii\desktop\rdirectx\dx12\dx12tutorial\dx12tutorial\</FILEPATH>
        <FILENAME>dx12wrapper.cpp</FILENAME>
        <LINE>392</LINE>
        <COLUMN>16</COLUMN>
      </SFA>
      <SFA>
        <FILEPATH>c:\users\sueyoshiii\desktop\rdirectx\dx12\dx12tutorial\dx12tutorial\</FILEPATH>
        <FILENAME>dx12wrapper.cpp</FILENAME>
        <LINE>393</LINE>
        <COLUMN>16</COLUMN>
      </SFA>
      <SFA>
        <FILEPATH>c:\users\sueyoshiii\desktop\rdirectx\dx12\dx12tutorial\dx12tutorial\</FILEPATH>
        <FILENAME>dx12wrapper.cpp</FILENAME>
        <LINE>394</LINE>
        <COLUMN>12</COLUMN>
      </SFA>
      <SFA>
        <FILEPATH>c:\users\sueyoshiii\desktop\rdirectx\dx12\dx12tutorial\dx12tutorial\</FILEPATH>
        <FILENAME>dx12wrapper.cpp</FILENAME>
        <LINE>395</LINE>
        <COLUMN>13</COLUMN>
      </SFA>
      <SFA>
        <FILEPATH>c:\users\sueyoshiii\desktop\rdirectx\dx12\dx12tutorial\dx12tutorial\</FILEPATH>
        <FILENAME>dx12wrapper.cpp</FILENAME>
        <LINE>396</LINE>
        <COLUMN>23</COLUMN>
      </SFA>
      <SFA>
        <FILEPATH>c:\users\sueyoshiii\desktop\rdirectx\dx12\dx12tutorial\dx12tutorial\</FILEPATH>
        <FILENAME>dx12wrapper.cpp</FILENAME>
        <LINE>397</LINE>
        <COLUMN>16</COLUMN>
      </SFA>
      <SFA>
        <FILEPATH>c:\users\sueyoshiii\desktop\rdirectx\dx12\dx12tutorial\dx12tutorial\</FILEPATH>
        <FILENAME>dx12wrapper.cpp</FILENAME>
        <LINE>398</LINE>
        <COLUMN>13</COLUMN>
      </SFA>
      <SFA>
        <FILEPATH>c:\users\sueyoshiii\desktop\rdirectx\dx12\dx12tutorial\dx12tutorial\</FILEPATH>
        <FILENAME>dx12wrapper.cpp</FILENAME>
        <LINE>399</LINE>
        <COLUMN>23</COLUMN>
      </SFA>
      <SFA>
        <FILEPATH>c:\users\sueyoshiii\desktop\rdirectx\dx12\dx12tutorial\dx12tutorial\</FILEPATH>
        <FILENAME>dx12wrapper.cpp</FILENAME>
        <LINE>400</LINE>
        <COLUMN>25</COLUMN>
      </SFA>
      <SFA>
        <FILEPATH>c:\users\sueyoshiii\desktop\rdirectx\dx12\dx12tutorial\dx12tutorial\</FILEPATH>
        <FILENAME>dx12wrapper.cpp</FILENAME>
        <LINE>401</LINE>
        <COLUMN>13</COLUMN>
      </SFA>
      <SFA>
        <FILEPATH>c:\users\sueyoshiii\desktop\rdirectx\dx12\dx12tutorial\dx12tutorial\</FILEPATH>
        <FILENAME>dx12wrapper.cpp</FILENAME>
        <LINE>402</LINE>
        <COLUMN>12</COLUMN>
      </SFA>
      <SFA>
        <FILEPATH>c:\users\sueyoshiii\desktop\rdirectx\dx12\dx12tutorial\dx12tutorial\</FILEPATH>
        <FILENAME>dx12wrapper.cpp</FILENAME>
        <LINE>404</LINE>
        <COLUMN>15</COLUMN>
      </SFA>
      <SFA>
        <FILEPATH>c:\users\sueyoshiii\desktop\rdirectx\dx12\dx12tutorial\dx12tutorial\</FILEPATH>
        <FILENAME>dx12wrapper.cpp</FILENAME>
        <LINE>405</LINE>
        <COLUMN>8</COLUMN>
        <KEYEVENT>
          <ID>1</ID>
          <KIND>宣言</KIND>
          <IMPORTANCE>Essential</IMPORTANCE>
          <MESSAGE>'texbuff' は NULL である可能性があります</MESSAGE>
        </KEYEVENT>
      </SFA>
      <SFA>
        <FILEPATH>c:\users\sueyoshiii\desktop\rdirectx\dx12\dx12tutorial\dx12tutorial\</FILEPATH>
        <FILENAME>dx12wrapper.cpp</FILENAME>
        <LINE>414</LINE>
        <COLUMN>20</COLUMN>
      </SFA>
      <SFA>
        <FILEPATH>c:\users\sueyoshiii\desktop\rdirectx\dx12\dx12tutorial\dx12tutorial\</FILEPATH>
        <FILENAME>dx12wrapper.cpp</FILENAME>
        <LINE>415</LINE>
        <COLUMN>17</COLUMN>
      </SFA>
      <SFA>
        <FILEPATH>c:\users\sueyoshiii\desktop\rdirectx\dx12\dx12tutorial\dx12tutorial\</FILEPATH>
        <FILENAME>dx12wrapper.cpp</FILENAME>
        <LINE>416</LINE>
        <COLUMN>28</COLUMN>
      </SFA>
      <SFA>
        <FILEPATH>c:\users\sueyoshiii\desktop\rdirectx\dx12\dx12tutorial\dx12tutorial\</FILEPATH>
        <FILENAME>dx12wrapper.cpp</FILENAME>
        <LINE>431</LINE>
        <COLUMN>8</COLUMN>
        <KEYEVENT>
          <ID>2</ID>
          <KIND>宣言</KIND>
          <IMPORTANCE>Full</IMPORTANCE>
          <MESSAGE>'texbuff' は 'ID3D12Resource::WriteToSubresource' からの出力です (c:\program files (x86)\windows kits\10\include\10.0.17134.0\um\d3d12.h:3960 で宣言)</MESSAGE>
        </KEYEVENT>
      </SFA>
      <SFA>
        <FILEPATH>c:\users\sueyoshiii\desktop\rdirectx\dx12\dx12tutorial\dx12tutorial\</FILEPATH>
        <FILENAME>dx12wrapper.cpp</FILENAME>
        <LINE>439</LINE>
        <COLUMN>24</COLUMN>
      </SFA>
      <SFA>
        <FILEPATH>c:\users\sueyoshiii\desktop\rdirectx\dx12\dx12tutorial\dx12tutorial\</FILEPATH>
        <FILENAME>dx12wrapper.cpp</FILENAME>
        <LINE>440</LINE>
        <COLUMN>19</COLUMN>
      </SFA>
      <SFA>
        <FILEPATH>c:\users\sueyoshiii\desktop\rdirectx\dx12\dx12tutorial\dx12tutorial\</FILEPATH>
        <FILENAME>dx12wrapper.cpp</FILENAME>
        <LINE>441</LINE>
        <COLUMN>29</COLUMN>
        <KEYEVENT>
          <ID>3</ID>
          <KIND>使用法</KIND>
          <IMPORTANCE>Full</IMPORTANCE>
          <MESSAGE>'texbuff' は 'CD3DX12_RESOURCE_BARRIER::Transition' への入力です (c:\users\sueyoshiii\desktop\rdirectx\dx12\dx12tutorial\dx12tutorial\d3dx12.h:734 で宣言)</MESSAGE>
        </KEYEVENT>
      </SFA>
      <SFA>
        <FILEPATH>c:\users\sueyoshiii\desktop\rdirectx\dx12\dx12tutorial\dx12tutorial\</FILEPATH>
        <FILENAME>dx12wrapper.cpp</FILENAME>
        <LINE>441</LINE>
        <COLUMN>29</COLUMN>
        <KEYEVENT>
          <ID>4</ID>
          <KIND>使用法</KIND>
          <IMPORTANCE>Essential</IMPORTANCE>
          <MESSAGE>'texbuff' を NULL にすることはできません。この値は 'CD3DX12_RESOURCE_BARRIER::Transition' の SAL 注釈と一致しません</MESSAGE>
        </KEYEVENT>
      </SFA>
    </PATH>
  </DEFECT>
</DEFECTS>